lingatagger/gender.py
lingatagger/genderlist.py
lingatagger/sentence.py
lingatagger/tagger.py
lingatagger/tokenizer.py
lingatagger-1.0.dist-info/DESCRIPTION.rst
lingatagger-1.0.dist-info/METADATA
lingatagger-1.0.dist-info/RECORD
lingatagger-1.0.dist-info/WHEEL
lingatagger-1.0.dist-info/metadata.json
lingatagger-1.0.dist-info/top_level.txt
